
    {
  "stats": {
    "Crit Damage": {
      "Primal": { "min": 25, "max": 35 },
      "Original": { "min": 30, "max": 35 },
      "Chaos": { "min": 35, "max": 40 },
      "Abyss": { "min": 40, "max": 45 },
      "Rune": { "min": 20, "max": 28 }
    },
    "Crit Chance": {
      "Primal": { "min": 6, "max": 12 },
      "Original": { "min": 8, "max": 12 },
      "Chaos": { "min": 10, "max": 14 },
      "Abyss": { "min": 12, "max": 14 },
      "Rune": { "min": 6, "max": 6 }
    },
    "Evasion": {
      "Primal": { "min": 12, "max": 14 },
      "Original": { "min": 12, "max": 14 },
      "Chaos": { "min": 14, "max": 16 },
      "Abyss": { "min": 16, "max": 18 },
      "Rune": { "min": 6, "max": 6 }
    }
  },
  "special": {
    "Weapon": ["Crit Damage +80%", "Transform to Demon Lord"],
    "Necklace": ["Crit Damage +60%"],
    "Ring": ["Crit Damage +60%"],
    "Helm": ["Boss Damage +25%", "HP% +52%"],
    "Chest": ["HP% +52%"],
    "Belt": ["DR% +40%"],
    "Gloves": ["Attack% +52%"],
    "Boots": ["Evasion +20%"]
  },
  "tiers": {
    "Primal": { "lines": 3, "special": false },
    "Original": { "lines": 4, "special": false },
    "Chaos": { "lines": 4, "special": true },
    "Abyss": { "lines": 4, "special": true }
  }
}
    "ATK SPD": {},
    "ATK%": {},
    "HP%": {},
    "DEF%": {},
    "DR%": {},
    "Boss Damage": {},
    "Primate Damage": {},
    "Undead Damage": {},
    "Demon Damage": {},
    "Animal Damage": {},
    "Monster Damage": {},
    "Lifesteal": {},
    "Skill Damage": {},
    "Weapon Skill": {},
    "Ignore Enemy DEF": {},
    "PvP Damage": {},
    "PvP Damage Reduction": {}
  },
